flask_sentry_requests_distributed_tracing/__init__.py
flask_sentry_requests_distributed_tracing-1.1.2.dist-info/METADATA
flask_sentry_requests_distributed_tracing-1.1.2.dist-info/WHEEL
flask_sentry_requests_distributed_tracing-1.1.2.dist-info/top_level.txt
flask_sentry_requests_distributed_tracing-1.1.2.dist-info/RECORD
