Metadata-Version: 2.1
Name: flask-sentry-requests-distributed-tracing
Version: 1.1.2
Summary: Utilities
Home-page: https://github.com/shuttl-tech/flask_sentry_requests_distributed_tracing
Author: Shuttl
Author-email: sherub.thakur@shuttl.com
License: MIT
Platform: UNKNOWN
Classifier: Programming Language :: Python :: 3.7
Requires-Dist: requests
Requires-Dist: sentry-sdk
Requires-Dist: flask
Provides-Extra: dev
Requires-Dist: flake8 ; extra == 'dev'
Provides-Extra: test
Requires-Dist: pytest ; extra == 'test'
Requires-Dist: pytest-runner ; extra == 'test'
Requires-Dist: pytest-cov ; extra == 'test'
Requires-Dist: pytest-pep8 ; extra == 'test'
Requires-Dist: responses ; extra == 'test'
